{
  "kind": "categoryToolbox",
  "contents": [
    {
      "kind": "category",
      "name": "Objects",
      "colour": 350,
      "contents": [
        {
          "kind": "block",
          "type": "rootobject"
        },
        {
          "kind": "block",
          "type": "arrayobject"
        },
        {
          "kind": "block",
          "type": "objectobject"
        }
      ]
    },
    {
      "kind": "category",
      "name": "Arrays",
      "colour": 220,
      "contents": [
        {
          "kind": "block",
          "type": "rootarray"
        },
        {
          "kind": "block",
          "type": "arrayarray"
        },
        {
          "kind": "block",
          "type": "objectarray"
        }
      ]
    },
    {
      "kind": "category",
      "name": "Strings",
      "colour": 60,
      "contents": [
        {
          "kind": "block",
          "type": "rootstring"
        },
        {
          "kind": "block",
          "type": "arraystring"
        },
        {
          "kind": "block",
          "type": "objectstring"
        }
      ]
    },
    {
      "kind": "category",
      "name": "Values",
      "colour": 120,
      "contents": [
        {
          "kind": "block",
          "type": "rootvalue"
        },
        {
          "kind": "block",
          "type": "arrayvalue"
        },
        {
          "kind": "block",
          "type": "objectvalue"
        }
      ]
    }
  ]
}